schwab_api/__init__.py
schwab_api/account_information.py
schwab_api/authentication.py
schwab_api/schwab.py
schwab_api/totp_generator.py
schwab_api/urls.py
schwab_api-0.4.3.dist-info/LICENSE
schwab_api-0.4.3.dist-info/METADATA
schwab_api-0.4.3.dist-info/WHEEL
schwab_api-0.4.3.dist-info/top_level.txt
schwab_api-0.4.3.dist-info/RECORD
